planly.py
planly-1.0.1.dist-info/licenses/LICENSE
planly-1.0.1.dist-info/METADATA
planly-1.0.1.dist-info/WHEEL
planly-1.0.1.dist-info/top_level.txt
planly-1.0.1.dist-info/RECORD
