Metadata-Version: 2.4
Name: planly
Version: 1.0.1
Summary: Official Python SDK for Planly subscription validation
Home-page: https://github.com/planly-dev/planly-python
Author: Planly.dev
License: MIT
Project-URL: Homepage, https://planly.dev
Project-URL: Documentation, https://docs.planly.dev
Project-URL: Repository, https://github.com/planly-dev/planly-python
Project-URL: Issues, https://github.com/planly-dev/planly-python/issues
Keywords: planly,subscription,validation,saas,billing
Classifier: Development Status :: 5 - Production/Stable
Classifier: Intended Audience :: Developers
Classifier: License :: OSI Approved :: MIT License
Classifier: Operating System :: OS Independent
Classifier: Programming Language :: Python :: 3
Classifier: Programming Language :: Python :: 3.7
Classifier: Programming Language :: Python :: 3.8
Classifier: Programming Language :: Python :: 3.9
Classifier: Programming Language :: Python :: 3.10
Classifier: Programming Language :: Python :: 3.11
Classifier: Programming Language :: Python :: 3.12
Requires-Python: >=3.7
License-File: LICENSE
Requires-Dist: requests>=2.25.0
Dynamic: home-page
Dynamic: license-file
Dynamic: requires-python
